pyconfreader.py
pyconfreader-0.5.dist-info/DESCRIPTION.rst
pyconfreader-0.5.dist-info/METADATA
pyconfreader-0.5.dist-info/RECORD
pyconfreader-0.5.dist-info/WHEEL
pyconfreader-0.5.dist-info/metadata.json
pyconfreader-0.5.dist-info/top_level.txt
